frost/__init__.py
frost/client.py
frost/models/__init__.py
frost/models/available_time_series_response.py
frost/models/observations_response.py
frost/models/sources_response.py
frost/tests/__init__.py
frost/tests/test_requests.py
frost_client-0.1.4.dist-info/LICENSE
frost_client-0.1.4.dist-info/METADATA
frost_client-0.1.4.dist-info/WHEEL
frost_client-0.1.4.dist-info/top_level.txt
frost_client-0.1.4.dist-info/RECORD
