Metadata-Version: 2.1
Name: frost-client
Version: 0.1.4
Summary: Python wrapper for the frost.met.no API
Home-page: https://github.com/BergensTidende/frost-client
Author: Anders G. Eriksen
Author-email: anders.eriksen@bt.no
License: MIT
Keywords: weather pandas
Platform: UNKNOWN
Classifier: Development Status :: 3 - Alpha
Classifier: License :: OSI Approved :: MIT License
Classifier: Programming Language :: Python :: 3.7
Classifier: Programming Language :: Python :: 3.6
Requires-Python: >= 3.6
Requires-Dist: requests
Provides-Extra: pandas
Requires-Dist: pandas ; extra == 'pandas'
